<xml xmlns="http://www.w3.org/1999/xhtml">
  <variables>
    <variable type="" id="7SN.7cfuIboDB35GIGcG">n</variable>
  </variables>
  <block type="variables_set" id="set_n_initial" inline="true" x="953" y="20">
    <field name="VAR" id="7SN.7cfuIboDB35GIGcG" variabletype="">n</field>
    <value name="VALUE">
      <block type="math_number" id="qqobsYdMF@/J-N{cfbG8">
        <field name="NUM">1</field>
      </block>
    </value>
    <next>
      <block type="controls_repeat_ext" id="repeat" inline="true">
        <value name="TIMES">
          <block type="math_number" id="a2pLuO(ITmGJB^^Ls$~e">
            <field name="NUM">4</field>
          </block>
        </value>
        <statement name="DO">
          <block type="variables_set" id="set_n_update" inline="true">
            <field name="VAR" id="7SN.7cfuIboDB35GIGcG" variabletype="">n</field>
            <value name="VALUE">
              <block type="math_arithmetic" id="Y$^Fm:dzDFx i!C{-]Fw">
                <field name="OP">ADD</field>
                <value name="A">
                  <block type="variables_get" id="YZ0cHn0$ZYf[_PllL .e">
                    <field name="VAR" id="7SN.7cfuIboDB35GIGcG" variabletype="">n</field>
                  </block>
                </value>
                <value name="B">
                  <block type="math_number" id="N=O,.oZQ?tY`-;x/Hu_b">
                    <field name="NUM">2</field>
                  </block>
                </value>
              </block>
            </value>
            <next>
              <block type="text_print" id="print">
                <value name="TEXT">
                  <block type="variables_get" id=".oIbQSAsd;hCb=%hh4OP">
                    <field name="VAR" id="7SN.7cfuIboDB35GIGcG" variabletype="">n</field>
                  </block>
                </value>
              </block>
            </next>
          </block>
        </statement>
      </block>
    </next>
  </block>
  <block type="text" id="M*md7[B%9nfPEBXB#%%j" x="1088" y="213">
    <field name="TEXT"></field>
  </block>
</xml>